{
	"skin-name": "concise",
	"preview-bg": "#6f84aa",
	"text": "#333366",
	"text-inverse": "#ffffff",
	"text-disabled": "#1d3f76",
	"has-gradients": true,
	"has-radius": true,
	"has-boxshadow": false,
	"has-button-borders": true,
	"btn-text": "#333366",
	"btn-text-shadow": "#ffffff",
	"btn-bg": "#ffffff",
	"btn-bg-hlight": "#dce8f1",
	"btn-border-top": "rgba(214,216,221,0.1)",
	"btn-border-right": "rgba(214,216,221,0.1)",
	"btn-border-bottom": "rgba(214,216,221,1)",
	"btn-border-left": "rgba(214,216,221,1)",
	"btn-split-border": "#333366",
	"btn-primary-text": "#ffffff",
	"btn-primary-text-shadow": "#333366",
	"btn-primary-bg": "#6f84aa",
	"btn-primary-bg-hlight": "#333366",
	"btn-padding": "4px 8px",
	"menu-bg": "#fafcff",
	"menu-border": "rgba(220,232,241,0.5)",
	"menuitem-text": "#333366",
	"menuitem-bg-selected": "#6f84aa",
	"menuitem-bg-selected-hlight": "#405b8e",
	"menuitem-separator-top": "#6f84aa",
	"menuitem-separator-bottom": "#ffffff",
	"menuitem-text-inverse": "#ffffff",
	"menuitem-bg-active": "#dce8f1",
	"menuitem-text-active": "#333366",
	"menuitem-preview-border-active": "#dce8f1",
	"menubar-menubtn-text": "",
	"checkbox-border": "#d6d8dd",
	"checkbox-border-focus": "#9facc6",
	"panel-border": "#d6d8dd",
	"panel-bg": "#ffffff",
	"panel-bg-hlight": "#fafcff",
	"textbox-bg": "#ffffff",
	"textbox-border": "#d6d8dd",
	"textbox-border-focus": "#dce8f1",
	"window-bg": "#ffffff",
	"window-border": "#dce8f1",
	"tab-bg": "#dce8f1",
	"tab-bg-hover": "#fafcff",
	"tab-bg-active": "#fafcff",
	"tab-border": "#d6d8dd",
	"tabs-bg": "#ffffff",
	"slider-bg": "#fafcff",
	"slider-border": "#d6d8dd",
	"slider-handle-bg": "#dce8f1",
	"slider-handle-border": "#d6d8dd",
	"colorbtn-backcolor-bg": "#ff9a20",
	"grid-border": "#6f84aa",
	"grid-border-active": "#dce8f1"
}